README.rst
setup.cfg
setup.py
betfair/__init__.py
betfair/betfair.py
betfair/constants.py
betfair/datatype.py
betfair/exceptions.py
betfair/models.py
betfair/price.py
betfair/utils.py
betfair.py.egg-info/PKG-INFO
betfair.py.egg-info/SOURCES.txt
betfair.py.egg-info/dependency_links.txt
betfair.py.egg-info/not-zip-safe
betfair.py.egg-info/requires.txt
betfair.py.egg-info/top_level.txt
betfair/meta/__init__.py
betfair/meta/models.py
betfair/meta/types.py
betfair/meta/utils.py