Metadata-Version: 1.1
Name: betfair.py
Version: 0.2.0
Summary: Python client for the Betfair API (https://api.developer.betfair.com/)
Home-page: https://github.com/jmcarp/betfair.py
Author: Joshua Carp
Author-email: jm.carp@gmail.com
License: UNKNOWN
Platform: UNKNOWN
Classifier: Development Status :: 4 - Beta
Classifier: Intended Audience :: Developers
Classifier: License :: OSI Approved :: MIT License
Classifier: Natural Language :: English
Classifier: Programming Language :: Python :: 2
Classifier: Programming Language :: Python :: 2.7
Classifier: Programming Language :: Python :: 3
Classifier: Programming Language :: Python :: 3.3
Classifier: Programming Language :: Python :: 3.4
Classifier: Programming Language :: Python :: Implementation :: PyPy
